helloworld.py
helloworld_notha99y-0.0.1.dist-info/LICENSE.txt
helloworld_notha99y-0.0.1.dist-info/METADATA
helloworld_notha99y-0.0.1.dist-info/WHEEL
helloworld_notha99y-0.0.1.dist-info/top_level.txt
helloworld_notha99y-0.0.1.dist-info/RECORD
